phystack/hub_client/__init__.py
phystack/hub_client/client.py
phystack/hub_client/twin_messaging.py
phystack/hub_client/twin_registry.py
phystack/hub_client/instances/__init__.py
phystack/hub_client/instances/base_instance.py
phystack/hub_client/instances/edge_instance.py
phystack/hub_client/instances/peripheral_instance.py
phystack/hub_client/services/__init__.py
phystack/hub_client/services/phyhub_connection.py
phystack/hub_client/services/webrtc/__init__.py
phystack/hub_client/services/webrtc/data_channel.py
phystack/hub_client/services/webrtc/media_stream.py
phystack/hub_client/types/__init__.py
phystack/hub_client/types/twin_types.py
phystack_hub_client-0.2.1.dist-info/METADATA
phystack_hub_client-0.2.1.dist-info/WHEEL
phystack_hub_client-0.2.1.dist-info/RECORD
