Metadata-Version: 2.4
Name: phystack-hub-client
Version: 0.2.1
Summary: Python client for PhyHub - events, actions, DataChannel, and MediaStream
Project-URL: Homepage, https://github.com/phystack/phystack-pypi
Project-URL: Documentation, https://docs.phystack.com
Project-URL: Repository, https://github.com/phystack/phystack-pypi
Author-email: Phystack <dev@phystack.com>
License-Expression: MIT
Classifier: Development Status :: 3 - Alpha
Classifier: Intended Audience :: Developers
Classifier: License :: OSI Approved :: MIT License
Classifier: Programming Language :: Python :: 3
Classifier: Programming Language :: Python :: 3.10
Classifier: Programming Language :: Python :: 3.11
Classifier: Programming Language :: Python :: 3.12
Requires-Python: >=3.10
Requires-Dist: aiohttp>=3.9.0
Requires-Dist: aiortc>=1.6.0
Requires-Dist: numpy>=1.24.0
Requires-Dist: opencv-python>=4.8.0
Requires-Dist: python-socketio[asyncio-client]>=5.10.0
Provides-Extra: dev
Requires-Dist: black>=23.0.0; extra == 'dev'
Requires-Dist: mypy>=1.5.0; extra == 'dev'
Requires-Dist: pytest-asyncio>=0.21.0; extra == 'dev'
Requires-Dist: pytest>=7.4.0; extra == 'dev'
Requires-Dist: ruff>=0.1.0; extra == 'dev'
